bynder_sdk/__init__.py
bynder_sdk/oauth2.py
bynder_sdk/permanent_token.py
bynder_sdk/util.py
bynder_sdk/version.py
bynder_sdk/client/__init__.py
bynder_sdk/client/asset_bank_client.py
bynder_sdk/client/bynder_client.py
bynder_sdk/client/collection_client.py
bynder_sdk/client/pim_client.py
bynder_sdk/client/upload_client.py
bynder_sdk/client/workflow_client.py
test/__init__.py
test/asset_bank_client_test.py
test/bynder_client_test.py
test/collection_client_test.py
test/oauth2_session_test.py
test/pim_client_test.py
test/workflow_client_test.py
bynder_sdk-2.0.2.dist-info/LICENSE
bynder_sdk-2.0.2.dist-info/METADATA
bynder_sdk-2.0.2.dist-info/WHEEL
bynder_sdk-2.0.2.dist-info/top_level.txt
bynder_sdk-2.0.2.dist-info/RECORD
