Metadata-Version: 2.1
Name: bynder-sdk
Version: 2.0.2
Summary: Bynder SDK can be used to speed up the integration of Bynder in Python
Home-page: https://bynder.com
Author: Bynder
Author-email: techteam@bynder.com
License: MIT
Keywords: bynder,dam
Classifier: Programming Language :: Python
Classifier: Programming Language :: Python :: 3
Classifier: Intended Audience :: Developers
Classifier: License :: OSI Approved :: Apache Software License
Classifier: Operating System :: OS Independent
Classifier: Topic :: Software Development :: Libraries :: Python Modules
License-File: LICENSE
Requires-Dist: requests<=3.0.0,>=2.20.0
Requires-Dist: requests-oauthlib<=2.0.0,>=1.1.0
